biotex/__init__.py
biotex/aminocode.py
biotex/dnabits.py
biotex/fastatools.py
biotex/searchtools.py
biotex/utilities.py
biotex/bag/__init__.py
biotex/bag/matlab_like.py
biotex/bag/text_operation/__init__.py
biotex/bag/text_operation/stopwords.txt
biotex/bag/text_operation/tm.py
biotex/collsci/__init__.py
biotex/collsci/brain.py
biotex/huflus/Novo Documento de Texto.txt
biotex/huflus/__init__.py
biotex/huflus/huflus.py
biotex-1.0.0.0.dist-info/METADATA
biotex-1.0.0.0.dist-info/WHEEL
biotex-1.0.0.0.dist-info/top_level.txt
biotex-1.0.0.0.dist-info/RECORD
