Metadata-Version: 2.1
Name: biotex
Version: 1.0.0.0
Summary: The biotext library offers resources to support text mining strategy using bioinformatics tool
Home-page: UNKNOWN
Author: Diogo de J. S. Machado
Author-email: diogomachado.bioinfo@gmail.com
License: UNKNOWN
Platform: UNKNOWN
Requires-Dist: numpy
Requires-Dist: pandas
Requires-Dist: unidecode
Requires-Dist: biopython
Requires-Dist: sweep
Requires-Dist: scipy
Requires-Dist: scikit-learn
Requires-Dist: matplotlib
